setup.cfg
setup.py
ssa_baby_names.py
ssa_baby_names.egg-info/PKG-INFO
ssa_baby_names.egg-info/SOURCES.txt
ssa_baby_names.egg-info/dependency_links.txt
ssa_baby_names.egg-info/requires.txt
ssa_baby_names.egg-info/top_level.txt