Metadata-Version: 1.1
Name: ssa-baby-names
Version: 2.1
Summary: Python wrapper for the Social Security Administration's Popular Baby Names service
Home-page: https://github.com/mileswwatkins/ssa_baby_names
Author: Miles Watkins
Author-email: miles.w.watkins@gmail.com
License: UNKNOWN
Download-URL: https://github.com/mileswwatkins/ssa_baby_names/tarball/2.1
Keywords: Social Security Administaration,SSA,baby names,popular names,names
Platform: UNKNOWN
